cleanup_nodemodule/__init__.py
cleanup_nodemodule/cli.py
cleanup_nodemodule/core.py
cleanup_nodemodule-0.1.1.dist-info/licenses/LICENSE
cleanup_nodemodule-0.1.1.dist-info/METADATA
cleanup_nodemodule-0.1.1.dist-info/WHEEL
cleanup_nodemodule-0.1.1.dist-info/entry_points.txt
cleanup_nodemodule-0.1.1.dist-info/top_level.txt
cleanup_nodemodule-0.1.1.dist-info/RECORD
