Metadata-Version: 2.4
Name: cleanup-nodemodule
Version: 0.1.1
Summary: Find and remove node_modules, .next and dist folders (dry-run default).
Author: sakil470004
License-Expression: MIT
Requires-Python: >=3.8
License-File: LICENSE
Dynamic: license-file
